PyGPUEnergy/__init__.py
PyGPUEnergy/context.py
PyGPUEnergy/decorator.py
PyGPUEnergy/monitor.py
PyGPUEnergy/utils.py
PyGPUEnergy/visualize.py
pygpuenergy-0.1.1.dist-info/METADATA
pygpuenergy-0.1.1.dist-info/WHEEL
pygpuenergy-0.1.1.dist-info/top_level.txt
pygpuenergy-0.1.1.dist-info/RECORD
