Metadata-Version: 2.4
Name: PyGPUEnergy
Version: 0.1.1
Summary: A package for monitoring GPU power and energy consumption
Home-page: https://github.com/shwgao/PyGPUEnergy
Author: Shouwei Gao
Author-email: gaosho@oregonstate.edu
Classifier: Development Status :: 3 - Alpha
Classifier: Intended Audience :: Science/Research
Classifier: License :: OSI Approved :: MIT License
Classifier: Programming Language :: Python :: 3.9
Requires-Python: >=3.9
Requires-Dist: pandas
Requires-Dist: matplotlib
Requires-Dist: torch
Provides-Extra: dev
Requires-Dist: pytest; extra == "dev"
Requires-Dist: pytest-cov; extra == "dev"
Dynamic: author
Dynamic: author-email
Dynamic: classifier
Dynamic: description
Dynamic: description-content-type
Dynamic: home-page
Dynamic: provides-extra
Dynamic: requires-dist
Dynamic: requires-python
Dynamic: summary
